nexiles/tools/api/__init__.py
nexiles/tools/api/apps.py
nexiles/tools/api/checkinout.py
nexiles/tools/api/content.py
nexiles/tools/api/defaults.py
nexiles/tools/api/document.py
nexiles/tools/api/files.py
nexiles/tools/api/log.py
nexiles/tools/api/main.py
nexiles/tools/api/query.py
nexiles/tools/api/serve.py
nexiles/tools/api/tree.py
nexiles/tools/api/utils.py
nexiles/tools/api/validators.py
nexiles/tools/api/version.py
nexiles/tools/api/zip.py
nexiles/tools/api/slumber/__init__.py
nexiles/tools/api/slumber/exceptions.py
nexiles/tools/api/slumber/serialize.py
nexiles/tools/api/tests/__init__.py
nexiles/tools/api/tests/test_defaults.py
nexiles/tools/api/tests/test_document.py
nexiles/tools/api/tests/test_main.py
nexiles/tools/api/tests/test_query.py
nexiles/tools/api/tests/test_tree.py
nexiles/tools/api/tests/test_validators.py
nexiles.tools.api-0.5.1.dist-info/METADATA
nexiles.tools.api-0.5.1.dist-info/WHEEL
nexiles.tools.api-0.5.1.dist-info/entry_points.txt
nexiles.tools.api-0.5.1.dist-info/top_level.txt
nexiles.tools.api-0.5.1.dist-info/RECORD
