Metadata-Version: 2.1
Name: nexiles.tools.api
Version: 0.5.1
Summary: nexiles.tools.api -- python nexiles Windchill gateway http client api
Home-page: http://nexiles.github.io/nexiles.tools.api/
Author: Stefan Eletzhofer
Author-email: stefan.eletzhofer@nexiles.com
License: BSD
Classifier: Intended Audience :: Developers
Classifier: Topic :: Software Development :: Libraries :: Python Modules
Requires-Dist: setuptools
Requires-Dist: requests
Requires-Dist: argparse
Requires-Dist: tabulate
